yunxiao/__init__.py
yunxiao/achievement.py
yunxiao/arrange.py
yunxiao/classes.py
yunxiao/consume.py
yunxiao/curriculum.py
yunxiao/order.py
yunxiao/page.py
yunxiao/report.py
yunxiao/student.py
yunxiao/teacher.py
yunxiao/trade.py
yunxiao/yunxiao.py
yunxiao-0.5.25.dist-info/METADATA
yunxiao-0.5.25.dist-info/WHEEL
yunxiao-0.5.25.dist-info/RECORD
