Metadata-Version: 2.1
Name: yunxiao
Version: 0.5.25
Summary: An API SDK tool for Cloud School Education Institution Management System.
Author: YiZixuan
Author-email: admin@sqkkzyx.com
Requires-Python: >=3.12,<4.0
Classifier: Programming Language :: Python :: 3
Classifier: Programming Language :: Python :: 3.12
